drift_bytes/_drift_bytes.cpython-38-darwin.so
drift_bytes/__init__.py
drift_bytes/bytes.py
drift_bytes/include/drift_bytes/bytes.h
drift_bytes/share/drift_bytes/cmake/drift_bytes-config-version.cmake
drift_bytes/share/drift_bytes/cmake/drift_bytes-config.cmake
drift_bytes/share/drift_bytes/cmake/drift_bytes-targets.cmake
drift_bytes-0.3.0.dist-info/RECORD
drift_bytes-0.3.0.dist-info/LICENSE
drift_bytes-0.3.0.dist-info/WHEEL
drift_bytes-0.3.0.dist-info/top_level.txt
drift_bytes-0.3.0.dist-info/METADATA
